async_flow_control/__init__.py
async_flow_control/async_throttler/__init__.py
async_flow_control/async_throttler/throttler_concurrency.py
async_flow_control/async_throttler/throttler_rate.py
async_flow_control/decorator/__init__.py
async_flow_control/decorator/decorator_spacer.py
async_flow_control/decorator/decorator_throttler.py
async_flow_control/decorator/decorator_timer.py
async_flow_control/timer/__init__.py
async_flow_control/timer/timer.py
async_flow_control/util/__init__.py
async_flow_control/util/base.py
async_flow_control/util/dummy_spacer.py
async_flow_control/util/exception.py
async_flow_control/util/task_spacer.py
async_flow_control-0.1.1.dist-info/LICENSE
async_flow_control-0.1.1.dist-info/METADATA
async_flow_control-0.1.1.dist-info/WHEEL
async_flow_control-0.1.1.dist-info/top_level.txt
async_flow_control-0.1.1.dist-info/RECORD
